[{"__symbolic":"module","version":3,"metadata":{"RegistrationEventResponse":{"__symbolic":"interface"},"NotificationEventResponse":{"__symbolic":"interface"},"NotificationEventAdditionalData":{"__symbolic":"interface"},"IOSPushOptions":{"__symbolic":"interface"},"CategoryArray":{"__symbolic":"interface"},"CategoryAction":{"__symbolic":"interface"},"CategoryActionData":{"__symbolic":"interface"},"AndroidPushOptions":{"__symbolic":"interface"},"PushOptions":{"__symbolic":"interface"},"Push":{"__symbolic":"class","extends":{"__symbolic":"reference","module":"@ionic-native/core","name":"IonicNativePlugin"},"decorators":[{"__symbolic":"call","expression":{"__symbolic":"reference","module":"@ionic-native/core","name":"Plugin"},"arguments":[{"pluginName":"Push","plugin":"phonegap-plugin-push","pluginRef":"PushNotification","repo":"https://github.com/phonegap/phonegap-plugin-push","install":"ionic cordova plugin add phonegap-plugin-push --variable SENDER_ID=XXXXXXXXX","installVariables":["SENDER_ID"],"platforms":["Android","Browser","iOS","Windows"]}]},{"__symbolic":"call","expression":{"__symbolic":"reference","module":"@angular/core","name":"Injectable"}}],"members":{"init":[{"__symbolic":"method"}],"hasPermission":[{"__symbolic":"method","decorators":[{"__symbolic":"call","expression":{"__symbolic":"reference","module":"@ionic-native/core","name":"Cordova"}}]}]}},"PushObject":{"__symbolic":"class","decorators":[{"__symbolic":"call","expression":{"__symbolic":"reference","module":"@ionic-native/core","name":"Plugin"},"arguments":[{"pluginName":"Push","plugin":"phonegap-plugin-push","pluginRef":"PushNotification"}]}],"members":{"__ctor__":[{"__symbolic":"constructor","parameters":[{"__symbolic":"reference","name":"any"}]}],"on":[{"__symbolic":"method","decorators":[{"__symbolic":"call","expression":{"__symbolic":"reference","module":"@ionic-native/core","name":"CordovaInstance"},"arguments":[{"observable":true,"clearFunction":"off","clearWithArgs":true}]}]}],"unregister":[{"__symbolic":"method","decorators":[{"__symbolic":"call","expression":{"__symbolic":"reference","module":"@ionic-native/core","name":"CordovaInstance"}}]}],"setApplicationIconBadgeNumber":[{"__symbolic":"method","decorators":[{"__symbolic":"call","expression":{"__symbolic":"reference","module":"@ionic-native/core","name":"CordovaInstance"},"arguments":[{"callbackOrder":"reverse"}]}]}],"getApplicationIconBadgeNumber":[{"__symbolic":"method","decorators":[{"__symbolic":"call","expression":{"__symbolic":"reference","module":"@ionic-native/core","name":"CordovaInstance"}}]}],"finish":[{"__symbolic":"method","decorators":[{"__symbolic":"call","expression":{"__symbolic":"reference","module":"@ionic-native/core","name":"CordovaInstance"}}]}],"clearAllNotifications":[{"__symbolic":"method","decorators":[{"__symbolic":"call","expression":{"__symbolic":"reference","module":"@ionic-native/core","name":"CordovaInstance"}}]}],"subscribe":[{"__symbolic":"method","decorators":[{"__symbolic":"call","expression":{"__symbolic":"reference","module":"@ionic-native/core","name":"CordovaInstance"}}]}],"unsubscribe":[{"__symbolic":"method","decorators":[{"__symbolic":"call","expression":{"__symbolic":"reference","module":"@ionic-native/core","name":"CordovaInstance"}}]}]}}}},{"__symbolic":"module","version":1,"metadata":{"RegistrationEventResponse":{"__symbolic":"interface"},"NotificationEventResponse":{"__symbolic":"interface"},"NotificationEventAdditionalData":{"__symbolic":"interface"},"IOSPushOptions":{"__symbolic":"interface"},"CategoryArray":{"__symbolic":"interface"},"CategoryAction":{"__symbolic":"interface"},"CategoryActionData":{"__symbolic":"interface"},"AndroidPushOptions":{"__symbolic":"interface"},"PushOptions":{"__symbolic":"interface"},"Push":{"__symbolic":"class","extends":{"__symbolic":"reference","module":"@ionic-native/core","name":"IonicNativePlugin"},"decorators":[{"__symbolic":"call","expression":{"__symbolic":"reference","module":"@ionic-native/core","name":"Plugin"},"arguments":[{"pluginName":"Push","plugin":"phonegap-plugin-push","pluginRef":"PushNotification","repo":"https://github.com/phonegap/phonegap-plugin-push","install":"ionic cordova plugin add phonegap-plugin-push --variable SENDER_ID=XXXXXXXXX","installVariables":["SENDER_ID"],"platforms":["Android","Browser","iOS","Windows"]}]},{"__symbolic":"call","expression":{"__symbolic":"reference","module":"@angular/core","name":"Injectable"}}],"members":{"init":[{"__symbolic":"method"}],"hasPermission":[{"__symbolic":"method","decorators":[{"__symbolic":"call","expression":{"__symbolic":"reference","module":"@ionic-native/core","name":"Cordova"}}]}]}},"PushObject":{"__symbolic":"class","decorators":[{"__symbolic":"call","expression":{"__symbolic":"reference","module":"@ionic-native/core","name":"Plugin"},"arguments":[{"pluginName":"Push","plugin":"phonegap-plugin-push","pluginRef":"PushNotification"}]}],"members":{"__ctor__":[{"__symbolic":"constructor","parameters":[{"__symbolic":"reference","name":"any"}]}],"on":[{"__symbolic":"method","decorators":[{"__symbolic":"call","expression":{"__symbolic":"reference","module":"@ionic-native/core","name":"CordovaInstance"},"arguments":[{"observable":true,"clearFunction":"off","clearWithArgs":true}]}]}],"unregister":[{"__symbolic":"method","decorators":[{"__symbolic":"call","expression":{"__symbolic":"reference","module":"@ionic-native/core","name":"CordovaInstance"}}]}],"setApplicationIconBadgeNumber":[{"__symbolic":"method","decorators":[{"__symbolic":"call","expression":{"__symbolic":"reference","module":"@ionic-native/core","name":"CordovaInstance"},"arguments":[{"callbackOrder":"reverse"}]}]}],"getApplicationIconBadgeNumber":[{"__symbolic":"method","decorators":[{"__symbolic":"call","expression":{"__symbolic":"reference","module":"@ionic-native/core","name":"CordovaInstance"}}]}],"finish":[{"__symbolic":"method","decorators":[{"__symbolic":"call","expression":{"__symbolic":"reference","module":"@ionic-native/core","name":"CordovaInstance"}}]}],"clearAllNotifications":[{"__symbolic":"method","decorators":[{"__symbolic":"call","expression":{"__symbolic":"reference","module":"@ionic-native/core","name":"CordovaInstance"}}]}],"subscribe":[{"__symbolic":"method","decorators":[{"__symbolic":"call","expression":{"__symbolic":"reference","module":"@ionic-native/core","name":"CordovaInstance"}}]}],"unsubscribe":[{"__symbolic":"method","decorators":[{"__symbolic":"call","expression":{"__symbolic":"reference","module":"@ionic-native/core","name":"CordovaInstance"}}]}]}}}}]