[{"__symbolic":"module","version":3,"metadata":{"BackgroundGeolocationResponse":{"__symbolic":"interface"},"BackgroundGeolocationConfig":{"__symbolic":"interface"},"BackgroundGeolocation":{"__symbolic":"class","extends":{"__symbolic":"reference","module":"@ionic-native/core","name":"IonicNativePlugin"},"decorators":[{"__symbolic":"call","expression":{"__symbolic":"reference","module":"@ionic-native/core","name":"Plugin"},"arguments":[{"pluginName":"BackgroundGeolocation","plugin":"cordova-plugin-mauron85-background-geolocation","pluginRef":"backgroundGeolocation","repo":"https://github.com/mauron85/cordova-plugin-background-geolocation","platforms":["Android","iOS"]}]},{"__symbolic":"call","expression":{"__symbolic":"reference","module":"@angular/core","name":"Injectable"}}],"members":{"configure":[{"__symbolic":"method","decorators":[{"__symbolic":"call","expression":{"__symbolic":"reference","module":"@ionic-native/core","name":"Cordova"},"arguments":[{"callbackOrder":"reverse","observable":true}]}]}],"start":[{"__symbolic":"method","decorators":[{"__symbolic":"call","expression":{"__symbolic":"reference","module":"@ionic-native/core","name":"Cordova"}}]}],"stop":[{"__symbolic":"method","decorators":[{"__symbolic":"call","expression":{"__symbolic":"reference","module":"@ionic-native/core","name":"Cordova"}}]}],"finish":[{"__symbolic":"method","decorators":[{"__symbolic":"call","expression":{"__symbolic":"reference","module":"@ionic-native/core","name":"Cordova"},"arguments":[{"platforms":["iOS"]}]}]}],"changePace":[{"__symbolic":"method","decorators":[{"__symbolic":"call","expression":{"__symbolic":"reference","module":"@ionic-native/core","name":"Cordova"},"arguments":[{"platforms":["iOS"]}]}]}],"setConfig":[{"__symbolic":"method","decorators":[{"__symbolic":"call","expression":{"__symbolic":"reference","module":"@ionic-native/core","name":"Cordova"},"arguments":[{"callbackOrder":"reverse"}]}]}],"getStationaryLocation":[{"__symbolic":"method","decorators":[{"__symbolic":"call","expression":{"__symbolic":"reference","module":"@ionic-native/core","name":"Cordova"},"arguments":[{"platforms":["iOS"]}]}]}],"onStationary":[{"__symbolic":"method","decorators":[{"__symbolic":"call","expression":{"__symbolic":"reference","module":"@ionic-native/core","name":"Cordova"},"arguments":[{"platforms":["iOS"]}]}]}],"isLocationEnabled":[{"__symbolic":"method","decorators":[{"__symbolic":"call","expression":{"__symbolic":"reference","module":"@ionic-native/core","name":"Cordova"},"arguments":[{"platforms":["Android"]}]}]}],"showAppSettings":[{"__symbolic":"method","decorators":[{"__symbolic":"call","expression":{"__symbolic":"reference","module":"@ionic-native/core","name":"Cordova"},"arguments":[{"sync":true}]}]}],"showLocationSettings":[{"__symbolic":"method","decorators":[{"__symbolic":"call","expression":{"__symbolic":"reference","module":"@ionic-native/core","name":"Cordova"},"arguments":[{"sync":true}]}]}],"watchLocationMode":[{"__symbolic":"method","decorators":[{"__symbolic":"call","expression":{"__symbolic":"reference","module":"@ionic-native/core","name":"Cordova"},"arguments":[{"platforms":["Android"]}]}]}],"stopWatchingLocationMode":[{"__symbolic":"method","decorators":[{"__symbolic":"call","expression":{"__symbolic":"reference","module":"@ionic-native/core","name":"Cordova"},"arguments":[{"platforms":["Android"]}]}]}],"getLocations":[{"__symbolic":"method","decorators":[{"__symbolic":"call","expression":{"__symbolic":"reference","module":"@ionic-native/core","name":"Cordova"},"arguments":[{"platforms":["Android"]}]}]}],"getValidLocations":[{"__symbolic":"method","decorators":[{"__symbolic":"call","expression":{"__symbolic":"reference","module":"@ionic-native/core","name":"Cordova"}}]}],"deleteLocation":[{"__symbolic":"method","decorators":[{"__symbolic":"call","expression":{"__symbolic":"reference","module":"@ionic-native/core","name":"Cordova"},"arguments":[{"platforms":["Android"]}]}]}],"deleteAllLocations":[{"__symbolic":"method","decorators":[{"__symbolic":"call","expression":{"__symbolic":"reference","module":"@ionic-native/core","name":"Cordova"},"arguments":[{"platforms":["Android"]}]}]}],"switchMode":[{"__symbolic":"method","decorators":[{"__symbolic":"call","expression":{"__symbolic":"reference","module":"@ionic-native/core","name":"Cordova"},"arguments":[{"platforms":["iOS"]}]}]}],"getLogEntries":[{"__symbolic":"method","decorators":[{"__symbolic":"call","expression":{"__symbolic":"reference","module":"@ionic-native/core","name":"Cordova"}}]}]}}}},{"__symbolic":"module","version":1,"metadata":{"BackgroundGeolocationResponse":{"__symbolic":"interface"},"BackgroundGeolocationConfig":{"__symbolic":"interface"},"BackgroundGeolocation":{"__symbolic":"class","extends":{"__symbolic":"reference","module":"@ionic-native/core","name":"IonicNativePlugin"},"decorators":[{"__symbolic":"call","expression":{"__symbolic":"reference","module":"@ionic-native/core","name":"Plugin"},"arguments":[{"pluginName":"BackgroundGeolocation","plugin":"cordova-plugin-mauron85-background-geolocation","pluginRef":"backgroundGeolocation","repo":"https://github.com/mauron85/cordova-plugin-background-geolocation","platforms":["Android","iOS"]}]},{"__symbolic":"call","expression":{"__symbolic":"reference","module":"@angular/core","name":"Injectable"}}],"members":{"configure":[{"__symbolic":"method","decorators":[{"__symbolic":"call","expression":{"__symbolic":"reference","module":"@ionic-native/core","name":"Cordova"},"arguments":[{"callbackOrder":"reverse","observable":true}]}]}],"start":[{"__symbolic":"method","decorators":[{"__symbolic":"call","expression":{"__symbolic":"reference","module":"@ionic-native/core","name":"Cordova"}}]}],"stop":[{"__symbolic":"method","decorators":[{"__symbolic":"call","expression":{"__symbolic":"reference","module":"@ionic-native/core","name":"Cordova"}}]}],"finish":[{"__symbolic":"method","decorators":[{"__symbolic":"call","expression":{"__symbolic":"reference","module":"@ionic-native/core","name":"Cordova"},"arguments":[{"platforms":["iOS"]}]}]}],"changePace":[{"__symbolic":"method","decorators":[{"__symbolic":"call","expression":{"__symbolic":"reference","module":"@ionic-native/core","name":"Cordova"},"arguments":[{"platforms":["iOS"]}]}]}],"setConfig":[{"__symbolic":"method","decorators":[{"__symbolic":"call","expression":{"__symbolic":"reference","module":"@ionic-native/core","name":"Cordova"},"arguments":[{"callbackOrder":"reverse"}]}]}],"getStationaryLocation":[{"__symbolic":"method","decorators":[{"__symbolic":"call","expression":{"__symbolic":"reference","module":"@ionic-native/core","name":"Cordova"},"arguments":[{"platforms":["iOS"]}]}]}],"onStationary":[{"__symbolic":"method","decorators":[{"__symbolic":"call","expression":{"__symbolic":"reference","module":"@ionic-native/core","name":"Cordova"},"arguments":[{"platforms":["iOS"]}]}]}],"isLocationEnabled":[{"__symbolic":"method","decorators":[{"__symbolic":"call","expression":{"__symbolic":"reference","module":"@ionic-native/core","name":"Cordova"},"arguments":[{"platforms":["Android"]}]}]}],"showAppSettings":[{"__symbolic":"method","decorators":[{"__symbolic":"call","expression":{"__symbolic":"reference","module":"@ionic-native/core","name":"Cordova"},"arguments":[{"sync":true}]}]}],"showLocationSettings":[{"__symbolic":"method","decorators":[{"__symbolic":"call","expression":{"__symbolic":"reference","module":"@ionic-native/core","name":"Cordova"},"arguments":[{"sync":true}]}]}],"watchLocationMode":[{"__symbolic":"method","decorators":[{"__symbolic":"call","expression":{"__symbolic":"reference","module":"@ionic-native/core","name":"Cordova"},"arguments":[{"platforms":["Android"]}]}]}],"stopWatchingLocationMode":[{"__symbolic":"method","decorators":[{"__symbolic":"call","expression":{"__symbolic":"reference","module":"@ionic-native/core","name":"Cordova"},"arguments":[{"platforms":["Android"]}]}]}],"getLocations":[{"__symbolic":"method","decorators":[{"__symbolic":"call","expression":{"__symbolic":"reference","module":"@ionic-native/core","name":"Cordova"},"arguments":[{"platforms":["Android"]}]}]}],"getValidLocations":[{"__symbolic":"method","decorators":[{"__symbolic":"call","expression":{"__symbolic":"reference","module":"@ionic-native/core","name":"Cordova"}}]}],"deleteLocation":[{"__symbolic":"method","decorators":[{"__symbolic":"call","expression":{"__symbolic":"reference","module":"@ionic-native/core","name":"Cordova"},"arguments":[{"platforms":["Android"]}]}]}],"deleteAllLocations":[{"__symbolic":"method","decorators":[{"__symbolic":"call","expression":{"__symbolic":"reference","module":"@ionic-native/core","name":"Cordova"},"arguments":[{"platforms":["Android"]}]}]}],"switchMode":[{"__symbolic":"method","decorators":[{"__symbolic":"call","expression":{"__symbolic":"reference","module":"@ionic-native/core","name":"Cordova"},"arguments":[{"platforms":["iOS"]}]}]}],"getLogEntries":[{"__symbolic":"method","decorators":[{"__symbolic":"call","expression":{"__symbolic":"reference","module":"@ionic-native/core","name":"Cordova"}}]}]}}}}]