[{"__symbolic":"module","version":3,"metadata":{"PhotoLibrary":{"__symbolic":"class","extends":{"__symbolic":"reference","module":"@ionic-native/core","name":"IonicNativePlugin"},"decorators":[{"__symbolic":"call","expression":{"__symbolic":"reference","module":"@ionic-native/core","name":"Plugin"},"arguments":[{"pluginName":"PhotoLibrary","plugin":"cordova-plugin-photo-library","pluginRef":"cordova.plugins.photoLibrary","repo":"https://github.com/terikon/cordova-plugin-photo-library","install":"ionic cordova plugin add cordova-plugin-photo-library --variable PHOTO_LIBRARY_USAGE_DESCRIPTION=\"To choose photos\"","installVariables":["PHOTO_LIBRARY_USAGE_DESCRIPTION"],"platforms":["Android","Browser","iOS"]}]},{"__symbolic":"call","expression":{"__symbolic":"reference","module":"@angular/core","name":"Injectable"}}],"members":{"getLibrary":[{"__symbolic":"method","decorators":[{"__symbolic":"error","message":"Function call not supported","line":60,"character":26}]}],"requestAuthorization":[{"__symbolic":"method","decorators":[{"__symbolic":"call","expression":{"__symbolic":"reference","module":"@ionic-native/core","name":"Cordova"},"arguments":[{"callbackOrder":"reverse"}]}]}],"getAlbums":[{"__symbolic":"method","decorators":[{"__symbolic":"call","expression":{"__symbolic":"reference","module":"@ionic-native/core","name":"Cordova"},"arguments":[{"callbackOrder":"reverse"}]}]}],"getThumbnailURL":[{"__symbolic":"method","decorators":[{"__symbolic":"call","expression":{"__symbolic":"reference","module":"@ionic-native/core","name":"Cordova"},"arguments":[{"successIndex":1,"errorIndex":2}]}]}],"getPhotoURL":[{"__symbolic":"method","decorators":[{"__symbolic":"call","expression":{"__symbolic":"reference","module":"@ionic-native/core","name":"Cordova"},"arguments":[{"successIndex":1,"errorIndex":2}]}]}],"getThumbnail":[{"__symbolic":"method","decorators":[{"__symbolic":"call","expression":{"__symbolic":"reference","module":"@ionic-native/core","name":"Cordova"},"arguments":[{"successIndex":1,"errorIndex":2}]}]}],"getPhoto":[{"__symbolic":"method","decorators":[{"__symbolic":"call","expression":{"__symbolic":"reference","module":"@ionic-native/core","name":"Cordova"},"arguments":[{"successIndex":1,"errorIndex":2}]}]}],"saveImage":[{"__symbolic":"method","decorators":[{"__symbolic":"call","expression":{"__symbolic":"reference","module":"@ionic-native/core","name":"Cordova"},"arguments":[{"successIndex":2,"errorIndex":3}]}]}],"saveVideo":[{"__symbolic":"method","decorators":[{"__symbolic":"call","expression":{"__symbolic":"reference","module":"@ionic-native/core","name":"Cordova"},"arguments":[{"successIndex":2,"errorIndex":3}]}]}]}},"LibraryItem":{"__symbolic":"interface"},"AlbumItem":{"__symbolic":"interface"},"GetLibraryOptions":{"__symbolic":"interface"},"RequestAuthorizationOptions":{"__symbolic":"interface"},"GetThumbnailOptions":{"__symbolic":"interface"}}},{"__symbolic":"module","version":1,"metadata":{"PhotoLibrary":{"__symbolic":"class","extends":{"__symbolic":"reference","module":"@ionic-native/core","name":"IonicNativePlugin"},"decorators":[{"__symbolic":"call","expression":{"__symbolic":"reference","module":"@ionic-native/core","name":"Plugin"},"arguments":[{"pluginName":"PhotoLibrary","plugin":"cordova-plugin-photo-library","pluginRef":"cordova.plugins.photoLibrary","repo":"https://github.com/terikon/cordova-plugin-photo-library","install":"ionic cordova plugin add cordova-plugin-photo-library --variable PHOTO_LIBRARY_USAGE_DESCRIPTION=\"To choose photos\"","installVariables":["PHOTO_LIBRARY_USAGE_DESCRIPTION"],"platforms":["Android","Browser","iOS"]}]},{"__symbolic":"call","expression":{"__symbolic":"reference","module":"@angular/core","name":"Injectable"}}],"members":{"getLibrary":[{"__symbolic":"method","decorators":[{"__symbolic":"error","message":"Function call not supported","line":60,"character":26}]}],"requestAuthorization":[{"__symbolic":"method","decorators":[{"__symbolic":"call","expression":{"__symbolic":"reference","module":"@ionic-native/core","name":"Cordova"},"arguments":[{"callbackOrder":"reverse"}]}]}],"getAlbums":[{"__symbolic":"method","decorators":[{"__symbolic":"call","expression":{"__symbolic":"reference","module":"@ionic-native/core","name":"Cordova"},"arguments":[{"callbackOrder":"reverse"}]}]}],"getThumbnailURL":[{"__symbolic":"method","decorators":[{"__symbolic":"call","expression":{"__symbolic":"reference","module":"@ionic-native/core","name":"Cordova"},"arguments":[{"successIndex":1,"errorIndex":2}]}]}],"getPhotoURL":[{"__symbolic":"method","decorators":[{"__symbolic":"call","expression":{"__symbolic":"reference","module":"@ionic-native/core","name":"Cordova"},"arguments":[{"successIndex":1,"errorIndex":2}]}]}],"getThumbnail":[{"__symbolic":"method","decorators":[{"__symbolic":"call","expression":{"__symbolic":"reference","module":"@ionic-native/core","name":"Cordova"},"arguments":[{"successIndex":1,"errorIndex":2}]}]}],"getPhoto":[{"__symbolic":"method","decorators":[{"__symbolic":"call","expression":{"__symbolic":"reference","module":"@ionic-native/core","name":"Cordova"},"arguments":[{"successIndex":1,"errorIndex":2}]}]}],"saveImage":[{"__symbolic":"method","decorators":[{"__symbolic":"call","expression":{"__symbolic":"reference","module":"@ionic-native/core","name":"Cordova"},"arguments":[{"successIndex":2,"errorIndex":3}]}]}],"saveVideo":[{"__symbolic":"method","decorators":[{"__symbolic":"call","expression":{"__symbolic":"reference","module":"@ionic-native/core","name":"Cordova"},"arguments":[{"successIndex":2,"errorIndex":3}]}]}]}},"LibraryItem":{"__symbolic":"interface"},"AlbumItem":{"__symbolic":"interface"},"GetLibraryOptions":{"__symbolic":"interface"},"RequestAuthorizationOptions":{"__symbolic":"interface"},"GetThumbnailOptions":{"__symbolic":"interface"}}}]